CXCFmsMC/CXCFmsMC.py
CXCFmsMC/__init__.py
CXCFmsMC_binbin6106-1.0.3.dist-info/DESCRIPTION.rst
CXCFmsMC_binbin6106-1.0.3.dist-info/METADATA
CXCFmsMC_binbin6106-1.0.3.dist-info/RECORD
CXCFmsMC_binbin6106-1.0.3.dist-info/WHEEL
CXCFmsMC_binbin6106-1.0.3.dist-info/metadata.json
CXCFmsMC_binbin6106-1.0.3.dist-info/top_level.txt
