Metadata-Version: 2.0
Name: CXCFmsMC-binbin6106
Version: 1.0.3
Summary: A pkg to operate mitsubishi PLC by MCProtocol.
Home-page: UNKNOWN
Author: Wenbin
Author-email: zhangwenbin@mail.ujn.edu.cn
License: UNKNOWN
Platform: UNKNOWN
Classifier: Programming Language :: Python :: 3
Classifier: License :: OSI Approved :: MIT License
Classifier: Operating System :: Microsoft :: Windows :: Windows 10
